analysis/__init__.py
analysis/bon_to_alpacaeval.py
analysis/draw_model_histogram.py
analysis/draw_mtbench_analysis.py
analysis/draw_per_token_reward.py
analysis/draw_subtoken_statistics.py
analysis/get_benchmark_results.py
analysis/get_dpo_ref_free_results.py
analysis/get_per_token_reward.py
analysis/get_subtoken_statistics.py
analysis/plot_per_model_dist.py
analysis/plot_per_subset_dist.py
analysis/run_ensemble_offline.py
analysis/utils.py
analysis/visualization.py
rewardbench/__init__.py
rewardbench/chattemplates.py
rewardbench/constants.py
rewardbench/dpo.py
rewardbench/generative.py
rewardbench/generative_v2.py
rewardbench/rewardbench.py
rewardbench/utils.py
rewardbench/models/__init__.py
rewardbench/models/armorm.py
rewardbench/models/beaver.py
rewardbench/models/betterpairrm.py
rewardbench/models/grm.py
rewardbench/models/inform.py
rewardbench/models/internlm.py
rewardbench/models/ldlreward.py
rewardbench/models/openassistant.py
rewardbench/models/openbmb.py
rewardbench/models/pairrm.py
rewardbench/models/pipeline.py
rewardbench/models/qrm.py
rewardbench/models/shp.py
rewardbench/models/skyvl.py
rewardbench/models/slicpairpm.py
rewardbench/models/starling.py
rewardbench/models/worldpm.py
rewardbench/models/ziya.py
scripts/__init__.py
scripts/run_bon.py
scripts/run_dpo.py
scripts/run_generative.py
scripts/run_generative_v2.py
scripts/run_rm.py
scripts/run_v2.py
scripts/submit_eval_jobs.py
scripts/submit_eval_jobs_v2.py
scripts/submit_generative_jobs.py
tests/__init__.py
tests/test_data.py
tests/test_package.py
tests/test_utils.py
rewardbench-0.1.4.dist-info/LICENSE
rewardbench-0.1.4.dist-info/METADATA
rewardbench-0.1.4.dist-info/WHEEL
rewardbench-0.1.4.dist-info/entry_points.txt
rewardbench-0.1.4.dist-info/top_level.txt
rewardbench-0.1.4.dist-info/RECORD
