Metadata-Version: 2.2
Name: rewardbench
Version: 0.1.4
Summary: Tools for evaluating reward models
Home-page: https://github.com/allenai/rewardbench
Author: Nathan Lambert
Author-email: nathanl@allenai.org
Classifier: Programming Language :: Python :: 3
Classifier: License :: OSI Approved :: Apache Software License
Classifier: Operating System :: OS Independent
Requires-Python: >=3.10
License-File: LICENSE
Requires-Dist: accelerate
Requires-Dist: bitsandbytes
Requires-Dist: black
Requires-Dist: datasets
Requires-Dist: flake8>=6.0
Requires-Dist: fschat
Requires-Dist: huggingface_hub
Requires-Dist: hf_transfer
Requires-Dist: isort>=5.12.0
Requires-Dist: pandas
Requires-Dist: pytest
Requires-Dist: sentencepiece
Requires-Dist: tabulate
Requires-Dist: tokenizers
Requires-Dist: torch
Requires-Dist: tiktoken
Requires-Dist: transformers==4.51.0
Requires-Dist: trl>=0.8.2
Requires-Dist: wandb
Provides-Extra: generative
Requires-Dist: vllm==0.6.3; extra == "generative"
Requires-Dist: openai; extra == "generative"
Requires-Dist: anthropic; extra == "generative"
Requires-Dist: google-generativeai; extra == "generative"
Requires-Dist: together; extra == "generative"
Dynamic: author
Dynamic: author-email
Dynamic: classifier
Dynamic: description
Dynamic: description-content-type
Dynamic: home-page
Dynamic: provides-extra
Dynamic: requires-dist
Dynamic: requires-python
Dynamic: summary
